dc/__init__.py
dc/consts.py
dc/doctor.py
doctor/__init__.py
doctor/consts.py
doctor/doctor.py
doctor/reference/prefixes.tsv
doctor/reference/refine-class-uris.tsv
doctor/reference/refine-prefix-uris.tsv
rdf_doctor-1.2.0.dist-info/LICENSE
rdf_doctor-1.2.0.dist-info/METADATA
rdf_doctor-1.2.0.dist-info/WHEEL
rdf_doctor-1.2.0.dist-info/entry_points.txt
rdf_doctor-1.2.0.dist-info/top_level.txt
rdf_doctor-1.2.0.dist-info/RECORD
