Metadata-Version: 2.1
Name: rdf-doctor
Version: 1.2.0
Summary: Validate RDF data, report problems, and support creation of more accurate data
Home-page: https://github.com/dbcls/rdf-doctor
Author: DBCLS
License: MIT
Classifier: Programming Language :: Python :: 3.7
Classifier: Programming Language :: Python :: 3.8
Classifier: Programming Language :: Python :: 3.9
Classifier: Programming Language :: Python :: 3.10
Classifier: Programming Language :: Python :: 3.11
Classifier: Programming Language :: Python :: 3.12
License-File: LICENSE
Requires-Dist: Flask >=2.2.5
Requires-Dist: Flask-Cors >=3.0.9
Requires-Dist: rdflib >=6.3.1
Requires-Dist: SPARQLWrapper >=2.0.0
Requires-Dist: wlighter >=1.0.1
Requires-Dist: shexer >=2.4.1
Requires-Dist: unidecode >=1.3.6
Requires-Dist: python-xz
